__init__.py
main.py
devices/__init__.py
devices/device_type.py
devices/air_purifier/__init__.py
devices/air_purifier/h7126.py
devices/fan/__init__.py
devices/fan/h7102.py
devices/thermometer/__init__.py
devices/thermometer/h5179.py
devices/types/__init__.py
devices/types/air_purifier.py
devices/types/basic_fan.py
devices/types/fan.py
devices/types/thermometer.py
govee_cloud-20260126000023.dev0.dist-info/licenses/LICENSE
util/__init__.py
util/govee_api.py
util/govee_appliance_api.py
util/healthcheck.py
util/logging.py
govee_cloud-20260126000023.dev0.dist-info/METADATA
govee_cloud-20260126000023.dev0.dist-info/WHEEL
govee_cloud-20260126000023.dev0.dist-info/top_level.txt
govee_cloud-20260126000023.dev0.dist-info/RECORD
