Metadata-Version: 2.4
Name: govee-cloud
Version: 20260126000023.dev0
Summary: Govee Cloud API
Author-email: jnstockley <jnstockley@users.noreply.github.com>
Project-URL: Homepage, https://github.com/jnstockley/govee-cloud
Project-URL: Repository, https://github.com/jnstockley/govee-cloud.git
Project-URL: Issues, https://github.com/jnstockley/govee-cloud/issues
Keywords: starter,template,python
Classifier: Programming Language :: Python :: 3
Requires-Python: <4.0,>=3.13
License-File: LICENSE
Requires-Dist: aiohttp>=3.11.14
Requires-Dist: asyncio>=3.4.3
Requires-Dist: python-dotenv==1.2.1
Dynamic: license-file
